setup.py
line_pay_sdk/__init__.py
line_pay_sdk/base.py
line_pay_sdk/exceptions.py
line_pay_sdk/payment.py
line_pay_sdk/utils.py
line_pay_sdk.egg-info/PKG-INFO
line_pay_sdk.egg-info/SOURCES.txt
line_pay_sdk.egg-info/dependency_links.txt
line_pay_sdk.egg-info/requires.txt
line_pay_sdk.egg-info/top_level.txt