Metadata-Version: 1.0
Name: line-pay-sdk
Version: 0.0.1
Summary: just a simple line pay sdk
Home-page: UNKNOWN
Author: bamwang
Author-email: wangzhucn+dev@gmail.com
License: MIT License
Keywords: line,pay
Platform: any
